hydra_plugins/maze_local_launcher.py
maze/__init__.py
maze/maze_cli.py
maze/runner.py
maze/conf/__init__.py
maze/conf/conf_rollout.yaml
maze/conf/conf_train.yaml
maze/conf/algorithm/a2c.yaml
maze/conf/algorithm/bc.yaml
maze/conf/algorithm/es.yaml
maze/conf/algorithm/impala.yaml
maze/conf/algorithm/ppo.yaml
maze/conf/algorithm/sac.yaml
maze/conf/algorithm/sacfd.yaml
maze/conf/algorithm_configuration/a2c-test.yaml
maze/conf/algorithm_configuration/bc-test.yaml
maze/conf/algorithm_configuration/es-test.yaml
maze/conf/algorithm_configuration/impala-test.yaml
maze/conf/algorithm_configuration/ppo-test.yaml
maze/conf/algorithm_configuration/sac-test.yaml
maze/conf/algorithm_configuration/sacfd-test.yaml
maze/conf/algorithm_runner/a2c-dev.yaml
maze/conf/algorithm_runner/a2c-local.yaml
maze/conf/algorithm_runner/bc-dev.yaml
maze/conf/algorithm_runner/bc-local.yaml
maze/conf/algorithm_runner/es-dev.yaml
maze/conf/algorithm_runner/es-local.yaml
maze/conf/algorithm_runner/impala-dev.yaml
maze/conf/algorithm_runner/impala-local.yaml
maze/conf/algorithm_runner/ppo-dev.yaml
maze/conf/algorithm_runner/ppo-local.yaml
maze/conf/algorithm_runner/sac-dev.yaml
maze/conf/algorithm_runner/sac-local.yaml
maze/conf/algorithm_runner/sacfd-dev.yaml
maze/conf/algorithm_runner/sacfd-local.yaml
maze/conf/configuration/test.yaml
maze/conf/critic/flatten_concat_shared.yaml
maze/conf/critic/flatten_concat_state_action.yaml
maze/conf/critic/template_state.yaml
maze/conf/critic/template_state_action.yaml
maze/conf/env/gym_env.yaml
maze/conf/experiment/cartpole_ppo_wrappers.yaml
maze/conf/experiment/grid_search.yaml
maze/conf/experiment/nevergrad.yaml
maze/conf/model/flatten_concat.yaml
maze/conf/model/flatten_concat_shared_embedding.yaml
maze/conf/model/pixel_obs.yaml
maze/conf/model/pixel_obs_rnn.yaml
maze/conf/model/vector_obs.yaml
maze/conf/model/vector_obs_rnn.yaml
maze/conf/model_configuration/rllib-maze.yaml
maze/conf/model_configuration/rllib-test.yaml
maze_rl-0.2.0.dist-info/LICENSE.txt
maze_rl-0.2.0.dist-info/METADATA
maze_rl-0.2.0.dist-info/WHEEL
maze_rl-0.2.0.dist-info/entry_points.txt
maze_rl-0.2.0.dist-info/top_level.txt
maze_rl-0.2.0.dist-info/RECORD
