Metadata-Version: 2.1
Name: maze-rl
Version: 0.2.0
Summary: MazeRL is a development framework for building applied reinforcement learning systems, addressing real-world decision problems. It supports the complete development life cycle of RL applications, ranging from simulation engineering up to agent development, training and deployment.
Home-page: https://github.com/enlite-ai/maze
Author: enliteAI GmbH
Author-email: office@enlite.ai
License: MazeRL Software License (Research, Non-Commercial)
Keywords: applied-reinforcement-learning reinforcement-learning machine-learning deep-learning distributed optimization
Platform: UNKNOWN
Classifier: Development Status :: 3 - Alpha
Classifier: Intended Audience :: Developers
Classifier: Intended Audience :: Science/Research
Classifier: Intended Audience :: Education
Classifier: Topic :: Scientific/Engineering :: Artificial Intelligence
Classifier: Topic :: Software Development :: Libraries :: Python Modules
Classifier: License :: Other/Proprietary License
Classifier: Programming Language :: Python :: 3.7
Classifier: Programming Language :: Python :: 3.8
Classifier: Programming Language :: Python :: 3.9
Requires-Python: >=3.7
License-File: LICENSE.txt
Requires-Dist: tensorboard
Requires-Dist: pyyaml
Requires-Dist: requests
Requires-Dist: pillow
Requires-Dist: hydra-core (<1.2,>=1.1)
Requires-Dist: hydra-nevergrad-sweeper (>=1.3.0.dev0)
Requires-Dist: pandas
Requires-Dist: networkx
Requires-Dist: matplotlib
Requires-Dist: seaborn
Requires-Dist: tqdm
Requires-Dist: imageio
Requires-Dist: redis
Requires-Dist: cloudpickle
Requires-Dist: pytest (>=6.0.0)
Requires-Dist: pytest-timeout
Requires-Dist: pytest-redis
Requires-Dist: gym[box2d] (<0.23) ; python_version < "3.8"
Requires-Dist: pyglet (<2.0) ; python_version < "3.8"
Requires-Dist: gym (<0.23) ; python_version >= "3.8"
Provides-Extra: testing
Requires-Dist: pytest (>=6.0.0) ; extra == 'testing'
Requires-Dist: pytest-redis ; extra == 'testing'
